pyemojify-0.2.0.dist-info/RECORD
pyemojify-0.2.0.dist-info/WHEEL
pyemojify-0.2.0.dist-info/entry_points.txt
pyemojify-0.2.0.dist-info/DESCRIPTION.rst
pyemojify-0.2.0.dist-info/METADATA
pyemojify-0.2.0.dist-info/metadata.json
pyemojify-0.2.0.dist-info/top_level.txt
pyemojify/__init__.py
pyemojify/emojify.py
pyemojify/cli.py
pyemojify/emoji.py
