Metadata-Version: 1.1
Name: pyemojify
Version: 0.2.0
Summary: Substitutes emoji aliases (like :sparkling_heart:) to emoji raw characters.
Home-page: http://github.com/lord63/pyemojify
Author: lord63
Author-email: lord63.j@gmail.com
License: MIT
Keywords: emoji cli
Platform: UNKNOWN
Classifier: Development Status :: 4 - Beta
Classifier: Operating System :: POSIX
Classifier: Operating System :: POSIX :: Linux
Classifier: License :: OSI Approved :: MIT License
Classifier: Programming Language :: Python :: 2
Classifier: Programming Language :: Python :: 2.7
Classifier: Programming Language :: Python :: 3
Classifier: Programming Language :: Python :: 3.3
Classifier: Programming Language :: Python :: 3.4
Classifier: Programming Language :: Python :: 3.5
